CHANGELOG.rst
MANIFEST.in
README.rst
setup.cfg
setup.py
tox.ini
xunit2testrail/__init__.py
xunit2testrail/cmd.py
xunit2testrail/reporter.py
xunit2testrail/utils.py
xunit2testrail.egg-info/PKG-INFO
xunit2testrail.egg-info/SOURCES.txt
xunit2testrail.egg-info/dependency_links.txt
xunit2testrail.egg-info/entry_points.txt
xunit2testrail.egg-info/requires.txt
xunit2testrail.egg-info/top_level.txt
xunit2testrail/templates/testrail_comment.md
xunit2testrail/testrail/__init__.py
xunit2testrail/testrail/client.py
xunit2testrail/testrail/exceptions.py
xunit2testrail/vendor/__init__.py
xunit2testrail/vendor/xunitparser.py