Metadata-Version: 1.0
Name: xunit2testrail
Version: 0.7.3
Summary: Report test results from xUnit xml file to TestRail
Home-page: https://github.com/gdyuldin/testrail_reporter
Author: Georgy Dyuldin
Author-email: gdyuldin@mirantis.com
License: MIT
Platform: UNKNOWN
